alexandria3k/__init__.py
alexandria3k/__main__.py
alexandria3k/common.py
alexandria3k/csv_source.py
alexandria3k/data_source.py
alexandria3k/db_schema.py
alexandria3k/debug.py
alexandria3k/perf.py
alexandria3k/tsort.py
alexandria3k/uspto_zip_cache.py
alexandria3k/xml.py
alexandria3k/data/asjc.csv
alexandria3k/data_sources/asjcs.py
alexandria3k/data_sources/crossref.py
alexandria3k/data_sources/crossref_file_cache.py
alexandria3k/data_sources/datacite.py
alexandria3k/data_sources/doaj.py
alexandria3k/data_sources/funder_names.py
alexandria3k/data_sources/issn_subject_codes.py
alexandria3k/data_sources/journal_names.py
alexandria3k/data_sources/orcid.py
alexandria3k/data_sources/pubmed.py
alexandria3k/data_sources/pubmed_file_cache.py
alexandria3k/data_sources/ror.py
alexandria3k/data_sources/uspto.py
alexandria3k/data_sources/uspto_file_cache.py
alexandria3k/processes/link_aa_base_ror.py
alexandria3k/processes/link_aa_top_ror.py
alexandria3k/processes/link_uspto_doi.py
alexandria3k/processes/link_works_asjcs.py
alexandria3k/sql/get-issns.sql
alexandria3k/sql/link-works-asjcs.sql
alexandria3k/sql/normalize-asjc.sql
alexandria3k/sql/normalize-doaj.sql
alexandria3k/sql/normalize-journal-names-issns.sql
alexandria3k/sql/work-authors-top-rors.sql
alexandria3k-3.6.0.dist-info/METADATA
alexandria3k-3.6.0.dist-info/WHEEL
alexandria3k-3.6.0.dist-info/entry_points.txt
alexandria3k-3.6.0.dist-info/licenses/LICENSE
alexandria3k-3.6.0.dist-info/RECORD
