Metadata-Version: 2.3
Name: alexandria3k
Version: 3.6.0
Summary: Efficient relational database queries over the entire Crossref abnd ORCID data sets
Project-URL: Homepage, https://github.com/dspinellis/alexandria3k
Project-URL: Repository, https://github.com/dspinellis/alexandria3k.git
Project-URL: Bug Tracker, https://github.com/dspinellis/alexandria3k/issues
Project-URL: Documentation, https://dspinellis.github.io/alexandria3k/
Author-email: Diomidis Spinellis <dds@aueb.gr>
License:                     GNU GENERAL PUBLIC LICENSE
License-File: LICENSE
Classifier: Development Status :: 4 - Beta
Classifier: Environment :: Console
Classifier: Intended Audience :: Science/Research
Classifier: License :: OSI Approved :: GNU General Public License v3 or later (GPLv3+)
Classifier: Operating System :: OS Independent
Classifier: Programming Language :: Python :: 3
Classifier: Topic :: Database
Classifier: Topic :: Scientific/Engineering :: Information Analysis
Classifier: Topic :: Software Development :: Libraries :: Python Modules
Requires-Python: >=3.9
Requires-Dist: apsw
Requires-Dist: importlib-metadata
Requires-Dist: pyahocorasick
